PyVisionTools/ImageDraw.py
PyVisionTools/ImageProcessor.py
PyVisionTools/__init__.py
PyVisionTools/__main__.py
PyVisionTools/setup.py
PyVisionTools-0.0.8.dist-info/METADATA
PyVisionTools-0.0.8.dist-info/WHEEL
PyVisionTools-0.0.8.dist-info/top_level.txt
PyVisionTools-0.0.8.dist-info/RECORD
