Metadata-Version: 2.1
Name: PyVisionTools
Version: 0.0.8
Summary: A collection of tools for image processing
Home-page: https://github.com/Varenik2/PyVisionTools
Author: varenikGD
Author-email: arugula_baklava.0o@icloud.com
Classifier: Programming Language :: Python :: 3
Classifier: License :: OSI Approved :: MIT License
Classifier: Operating System :: OS Independent
Requires-Python: >=3.10.0
